{
	"data": [
		{
            "type": "其它API",
            "title": "javascript流行库汇总",
            "url": "http://cnodejs.org/topic/56ef3edd532839c33a99d00e"
        },
        {
            "type": "其它API",
            "title": "验证api",
            "url": "http://niceue.com/validator/demo/index.php"
        },
        {
            "type": "其它API",
            "title": "underscore 中文手册",
            "url": "http://www.css88.com/doc/underscore/"
        },
        {
            "type": "其它API",
            "title": "underscore源码分析",
            "url": "http://www.html-js.com/article/Underscorejs-source-code-analysis-of-underscorejs-source-code-analysis%25203031"
        },
        {
            "type": "其它API",
            "title": "underscore源码分析-亚里士朱德的博客",
            "url": "http://yalishizhude.github.io/tags/underscore/"
        },
        {
            "type": "其它API",
            "title": "underscrejs en api",
            "url": "http://underscorejs.org/"
        },
        {
            "type": "其它API",
            "title": "lodash - underscore的代替品",
            "url": "https://lodash.com/"
        },
        {
            "type": "其它API",
            "title": "ext4api",
            "url": "http://extjs-doc-cn.github.io/ext4api/"
        },
        {
            "type": "其它API",
            "title": "backbone 中文手册",
            "url": "http://www.csser.com/tools/backbone/backbone.js.html"
        },
        {
            "type": "其它API",
            "title": "qwrap手册",
            "url": "http://dev.qwrap.com/resource/js/_docs/_youa/%23/qw/base/loadJs_.htm"
        },
        {
            "type": "其它API",
            "title": "缓动函数",
            "url": "http://easings.net/zh-cn"
        },
        {
            "type": "其它API",
            "title": "svg 中文参考",
            "url": "http://www.w3school.com.cn/svg/svg_reference.asp"
        },
        {
            "type": "其它API",
            "title": "svg mdn参考",
            "url": "https://developer.mozilla.org/en-US/docs/Web/SVG"
        },
        {
            "type": "其它API",
            "title": "svg 导出 canvas",
            "url": "https://github.com/gabelerner/canvg"
        },
        {
            "type": "其它API",
            "title": "svg 导出 png",
            "url": "https://github.com/exupero/saveSvgAsPng"
        },
        {
            "type": "其它API",
            "title": "ai-to-svg",
            "url": "http://www.zamzar.com/convert/ai-to-svg/"
        },
        {
            "type": "其它API",
            "title": "localStorage 库",
            "url": "https://github.com/machao/localStorage"
        }
	]
}